{"openapi":"3.0.3","info":{"title":"TableRise - dungeons&dragons5e","contact":{"email":"tablerise@outlook.com","name":"tablerise"},"license":{"name":"MIT","url":"https://opensource.org/licenses/MIT"},"version":"3.0.0"},"servers":[{"url":"http://localhost:3001"}],"tags":[{"name":"armors"},{"name":"backgrounds"},{"name":"classes"},{"name":"feats"},{"name":"gods"},{"name":"items"},{"name":"races"},{"name":"realms"},{"name":"magicItems"},{"name":"monsters"},{"name":"spells"}],"paths":{"/dnd5e/armors":{"get":{"tags":["armors"],"responses":{"200":{"description":"OK"},"400":{"description":"Bad Request"},"401":{"description":"Unauthorized"},"403":{"description":"Forbidden"},"404":{"description":"Not Found"},"422":{"description":"Unprocessable Entity"},"500":{"description":"Internal"}},"security":[{"bearerAuth":[]}]}},"/dnd5e/armors/disabled":{"get":{"tags":["armors"],"responses":{"200":{"description":"OK"},"400":{"description":"Bad Request"},"401":{"description":"Unauthorized"},"403":{"description":"Forbidden"},"404":{"description":"Not Found"},"422":{"description":"Unprocessable Entity"},"500":{"description":"Internal"}},"security":[{"bearerAuth":[]}]}},"/dnd5e/armors/{id}":{"get":{"tags":["armors"],"responses":{"200":{"description":"OK"},"400":{"description":"Bad Request"},"401":{"description":"Unauthorized"},"403":{"description":"Forbidden"},"404":{"description":"Not Found"},"422":{"description":"Unprocessable Entity"},"500":{"description":"Internal"}},"security":[{"bearerAuth":[]}],"parameters":[{"name":"id","in":"path","required":true,"schema":{"type":"string"}}]},"patch":{"tags":["armors"],"responses":{"200":{"description":"OK"},"400":{"description":"Bad Request"},"401":{"description":"Unauthorized"},"403":{"description":"Forbidden"},"404":{"description":"Not Found"},"422":{"description":"Unprocessable Entity"},"500":{"description":"Internal"}},"security":[{"bearerAuth":[]}],"parameters":[{"name":"id","in":"path","required":true,"schema":{"type":"string"}},{"name":"availability","in":"query","required":true,"schema":{"type":"boolean"}}]}},"/dnd5e/backgrounds":{"get":{"tags":["backgrounds"],"responses":{"200":{"description":"OK"},"400":{"description":"Bad Request"},"401":{"description":"Unauthorized"},"403":{"description":"Forbidden"},"404":{"description":"Not Found"},"422":{"description":"Unprocessable Entity"},"500":{"description":"Internal"}},"security":[{"bearerAuth":[]}]}},"/dnd5e/backgrounds/disabled":{"get":{"tags":["backgrounds"],"responses":{"200":{"description":"OK"},"400":{"description":"Bad Request"},"401":{"description":"Unauthorized"},"403":{"description":"Forbidden"},"404":{"description":"Not Found"},"422":{"description":"Unprocessable Entity"},"500":{"description":"Internal"}},"security":[{"bearerAuth":[]}]}},"/dnd5e/backgrounds/{id}":{"get":{"tags":["backgrounds"],"responses":{"200":{"description":"OK"},"400":{"description":"Bad Request"},"401":{"description":"Unauthorized"},"403":{"description":"Forbidden"},"404":{"description":"Not Found"},"422":{"description":"Unprocessable Entity"},"500":{"description":"Internal"}},"security":[{"bearerAuth":[]}],"parameters":[{"name":"id","in":"path","required":true,"schema":{"type":"string"}}]},"patch":{"tags":["backgrounds"],"responses":{"200":{"description":"OK"},"400":{"description":"Bad Request"},"401":{"description":"Unauthorized"},"403":{"description":"Forbidden"},"404":{"description":"Not Found"},"422":{"description":"Unprocessable Entity"},"500":{"description":"Internal"}},"security":[{"bearerAuth":[]}],"parameters":[{"name":"id","in":"path","required":true,"schema":{"type":"string"}},{"name":"availability","in":"query","required":true,"schema":{"type":"boolean"}}]}},"/dnd5e/classes":{"get":{"tags":["classes"],"responses":{"200":{"description":"OK"},"400":{"description":"Bad Request"},"401":{"description":"Unauthorized"},"403":{"description":"Forbidden"},"404":{"description":"Not Found"},"422":{"description":"Unprocessable Entity"},"500":{"description":"Internal"}},"security":[{"bearerAuth":[]}]}},"/dnd5e/classes/disabled":{"get":{"tags":["classes"],"responses":{"200":{"description":"OK"},"400":{"description":"Bad Request"},"401":{"description":"Unauthorized"},"403":{"description":"Forbidden"},"404":{"description":"Not Found"},"422":{"description":"Unprocessable Entity"},"500":{"description":"Internal"}},"security":[{"bearerAuth":[]}]}},"/dnd5e/classes/{id}":{"get":{"tags":["classes"],"responses":{"200":{"description":"OK"},"400":{"description":"Bad Request"},"401":{"description":"Unauthorized"},"403":{"description":"Forbidden"},"404":{"description":"Not Found"},"422":{"description":"Unprocessable Entity"},"500":{"description":"Internal"}},"security":[{"bearerAuth":[]}],"parameters":[{"name":"id","in":"path","required":true,"schema":{"type":"string"}}]},"patch":{"tags":["classes"],"responses":{"200":{"description":"OK"},"400":{"description":"Bad Request"},"401":{"description":"Unauthorized"},"403":{"description":"Forbidden"},"404":{"description":"Not Found"},"422":{"description":"Unprocessable Entity"},"500":{"description":"Internal"}},"security":[{"bearerAuth":[]}],"parameters":[{"name":"id","in":"path","required":true,"schema":{"type":"string"}},{"name":"availability","in":"query","required":true,"schema":{"type":"boolean"}}]}},"/dnd5e/feats":{"get":{"tags":["feats"],"responses":{"200":{"description":"OK"},"400":{"description":"Bad Request"},"401":{"description":"Unauthorized"},"403":{"description":"Forbidden"},"404":{"description":"Not Found"},"422":{"description":"Unprocessable Entity"},"500":{"description":"Internal"}},"security":[{"bearerAuth":[]}]}},"/dnd5e/feats/disabled":{"get":{"tags":["feats"],"responses":{"200":{"description":"OK"},"400":{"description":"Bad Request"},"401":{"description":"Unauthorized"},"403":{"description":"Forbidden"},"404":{"description":"Not Found"},"422":{"description":"Unprocessable Entity"},"500":{"description":"Internal"}},"security":[{"bearerAuth":[]}]}},"/dnd5e/feats/{id}":{"get":{"tags":["feats"],"responses":{"200":{"description":"OK"},"400":{"description":"Bad Request"},"401":{"description":"Unauthorized"},"403":{"description":"Forbidden"},"404":{"description":"Not Found"},"422":{"description":"Unprocessable Entity"},"500":{"description":"Internal"}},"security":[{"bearerAuth":[]}],"parameters":[{"name":"id","in":"path","required":true,"schema":{"type":"string"}}]},"patch":{"tags":["feats"],"responses":{"200":{"description":"OK"},"400":{"description":"Bad Request"},"401":{"description":"Unauthorized"},"403":{"description":"Forbidden"},"404":{"description":"Not Found"},"422":{"description":"Unprocessable Entity"},"500":{"description":"Internal"}},"security":[{"bearerAuth":[]}],"parameters":[{"name":"id","in":"path","required":true,"schema":{"type":"string"}},{"name":"availability","in":"query","required":true,"schema":{"type":"boolean"}}]}},"/dnd5e/gods":{"get":{"tags":["gods"],"responses":{"200":{"description":"OK"},"400":{"description":"Bad Request"},"401":{"description":"Unauthorized"},"403":{"description":"Forbidden"},"404":{"description":"Not Found"},"422":{"description":"Unprocessable Entity"},"500":{"description":"Internal"}},"security":[{"bearerAuth":[]}]}},"/dnd5e/gods/disabled":{"get":{"tags":["gods"],"responses":{"200":{"description":"OK"},"400":{"description":"Bad Request"},"401":{"description":"Unauthorized"},"403":{"description":"Forbidden"},"404":{"description":"Not Found"},"422":{"description":"Unprocessable Entity"},"500":{"description":"Internal"}},"security":[{"bearerAuth":[]}]}},"/dnd5e/gods/{id}":{"get":{"tags":["gods"],"responses":{"200":{"description":"OK"},"400":{"description":"Bad Request"},"401":{"description":"Unauthorized"},"403":{"description":"Forbidden"},"404":{"description":"Not Found"},"422":{"description":"Unprocessable Entity"},"500":{"description":"Internal"}},"security":[{"bearerAuth":[]}],"parameters":[{"name":"id","in":"path","required":true,"schema":{"type":"string"}}]},"patch":{"tags":["gods"],"responses":{"200":{"description":"OK"},"400":{"description":"Bad Request"},"401":{"description":"Unauthorized"},"403":{"description":"Forbidden"},"404":{"description":"Not Found"},"422":{"description":"Unprocessable Entity"},"500":{"description":"Internal"}},"security":[{"bearerAuth":[]}],"parameters":[{"name":"id","in":"path","required":true,"schema":{"type":"string"}},{"name":"availability","in":"query","required":true,"schema":{"type":"boolean"}}]}},"/dnd5e/items":{"get":{"tags":["items"],"responses":{"200":{"description":"OK"},"400":{"description":"Bad Request"},"401":{"description":"Unauthorized"},"403":{"description":"Forbidden"},"404":{"description":"Not Found"},"422":{"description":"Unprocessable Entity"},"500":{"description":"Internal"}},"security":[{"bearerAuth":[]}]}},"/dnd5e/items/disabled":{"get":{"tags":["items"],"responses":{"200":{"description":"OK"},"400":{"description":"Bad Request"},"401":{"description":"Unauthorized"},"403":{"description":"Forbidden"},"404":{"description":"Not Found"},"422":{"description":"Unprocessable Entity"},"500":{"description":"Internal"}},"security":[{"bearerAuth":[]}]}},"/dnd5e/items/{id}":{"get":{"tags":["items"],"responses":{"200":{"description":"OK"},"400":{"description":"Bad Request"},"401":{"description":"Unauthorized"},"403":{"description":"Forbidden"},"404":{"description":"Not Found"},"422":{"description":"Unprocessable Entity"},"500":{"description":"Internal"}},"security":[{"bearerAuth":[]}],"parameters":[{"name":"id","in":"path","required":true,"schema":{"type":"string"}}]},"patch":{"tags":["items"],"responses":{"200":{"description":"OK"},"400":{"description":"Bad Request"},"401":{"description":"Unauthorized"},"403":{"description":"Forbidden"},"404":{"description":"Not Found"},"422":{"description":"Unprocessable Entity"},"500":{"description":"Internal"}},"security":[{"bearerAuth":[]}],"parameters":[{"name":"id","in":"path","required":true,"schema":{"type":"string"}},{"name":"availability","in":"query","required":true,"schema":{"type":"boolean"}}]}},"/dnd5e/races":{"get":{"tags":["races"],"responses":{"200":{"description":"OK"},"400":{"description":"Bad Request"},"401":{"description":"Unauthorized"},"403":{"description":"Forbidden"},"404":{"description":"Not Found"},"422":{"description":"Unprocessable Entity"},"500":{"description":"Internal"}},"security":[{"bearerAuth":[]}]}},"/dnd5e/races/disabled":{"get":{"tags":["races"],"responses":{"200":{"description":"OK"},"400":{"description":"Bad Request"},"401":{"description":"Unauthorized"},"403":{"description":"Forbidden"},"404":{"description":"Not Found"},"422":{"description":"Unprocessable Entity"},"500":{"description":"Internal"}},"security":[{"bearerAuth":[]}]}},"/dnd5e/races/{id}":{"get":{"tags":["races"],"responses":{"200":{"description":"OK"},"400":{"description":"Bad Request"},"401":{"description":"Unauthorized"},"403":{"description":"Forbidden"},"404":{"description":"Not Found"},"422":{"description":"Unprocessable Entity"},"500":{"description":"Internal"}},"security":[{"bearerAuth":[]}],"parameters":[{"name":"id","in":"path","required":true,"schema":{"type":"string"}}]},"patch":{"tags":["races"],"responses":{"200":{"description":"OK"},"400":{"description":"Bad Request"},"401":{"description":"Unauthorized"},"403":{"description":"Forbidden"},"404":{"description":"Not Found"},"422":{"description":"Unprocessable Entity"},"500":{"description":"Internal"}},"security":[{"bearerAuth":[]}],"parameters":[{"name":"id","in":"path","required":true,"schema":{"type":"string"}},{"name":"availability","in":"query","required":true,"schema":{"type":"boolean"}}]}},"/dnd5e/realms":{"get":{"tags":["realms"],"responses":{"200":{"description":"OK"},"400":{"description":"Bad Request"},"401":{"description":"Unauthorized"},"403":{"description":"Forbidden"},"404":{"description":"Not Found"},"422":{"description":"Unprocessable Entity"},"500":{"description":"Internal"}},"security":[{"bearerAuth":[]}]}},"/dnd5e/realms/disabled":{"get":{"tags":["realms"],"responses":{"200":{"description":"OK"},"400":{"description":"Bad Request"},"401":{"description":"Unauthorized"},"403":{"description":"Forbidden"},"404":{"description":"Not Found"},"422":{"description":"Unprocessable Entity"},"500":{"description":"Internal"}},"security":[{"bearerAuth":[]}]}},"/dnd5e/realms/{id}":{"get":{"tags":["realms"],"responses":{"200":{"description":"OK"},"400":{"description":"Bad Request"},"401":{"description":"Unauthorized"},"403":{"description":"Forbidden"},"404":{"description":"Not Found"},"422":{"description":"Unprocessable Entity"},"500":{"description":"Internal"}},"security":[{"bearerAuth":[]}],"parameters":[{"name":"id","in":"path","required":true,"schema":{"type":"string"}}]},"patch":{"tags":["realms"],"responses":{"200":{"description":"OK"},"400":{"description":"Bad Request"},"401":{"description":"Unauthorized"},"403":{"description":"Forbidden"},"404":{"description":"Not Found"},"422":{"description":"Unprocessable Entity"},"500":{"description":"Internal"}},"security":[{"bearerAuth":[]}],"parameters":[{"name":"id","in":"path","required":true,"schema":{"type":"string"}},{"name":"availability","in":"query","required":true,"schema":{"type":"boolean"}}]}},"/dnd5e/magicItems":{"get":{"tags":["magicItems"],"responses":{"200":{"description":"OK"},"400":{"description":"Bad Request"},"401":{"description":"Unauthorized"},"403":{"description":"Forbidden"},"404":{"description":"Not Found"},"422":{"description":"Unprocessable Entity"},"500":{"description":"Internal"}},"security":[{"bearerAuth":[]}]}},"/dnd5e/magicItems/disabled":{"get":{"tags":["magicItems"],"responses":{"200":{"description":"OK"},"400":{"description":"Bad Request"},"401":{"description":"Unauthorized"},"403":{"description":"Forbidden"},"404":{"description":"Not Found"},"422":{"description":"Unprocessable Entity"},"500":{"description":"Internal"}},"security":[{"bearerAuth":[]}]}},"/dnd5e/magicItems/{id}":{"get":{"tags":["magicItems"],"responses":{"200":{"description":"OK"},"400":{"description":"Bad Request"},"401":{"description":"Unauthorized"},"403":{"description":"Forbidden"},"404":{"description":"Not Found"},"422":{"description":"Unprocessable Entity"},"500":{"description":"Internal"}},"security":[{"bearerAuth":[]}],"parameters":[{"name":"id","in":"path","required":true,"schema":{"type":"string"}}]},"patch":{"tags":["magicItems"],"responses":{"200":{"description":"OK"},"400":{"description":"Bad Request"},"401":{"description":"Unauthorized"},"403":{"description":"Forbidden"},"404":{"description":"Not Found"},"422":{"description":"Unprocessable Entity"},"500":{"description":"Internal"}},"security":[{"bearerAuth":[]}],"parameters":[{"name":"id","in":"path","required":true,"schema":{"type":"string"}},{"name":"availability","in":"query","required":true,"schema":{"type":"boolean"}}]}},"/dnd5e/monsters":{"get":{"tags":["monsters"],"responses":{"200":{"description":"OK"},"400":{"description":"Bad Request"},"401":{"description":"Unauthorized"},"403":{"description":"Forbidden"},"404":{"description":"Not Found"},"422":{"description":"Unprocessable Entity"},"500":{"description":"Internal"}},"security":[{"bearerAuth":[]}]}},"/dnd5e/monsters/disabled":{"get":{"tags":["monsters"],"responses":{"200":{"description":"OK"},"400":{"description":"Bad Request"},"401":{"description":"Unauthorized"},"403":{"description":"Forbidden"},"404":{"description":"Not Found"},"422":{"description":"Unprocessable Entity"},"500":{"description":"Internal"}},"security":[{"bearerAuth":[]}]}},"/dnd5e/monsters/{id}":{"get":{"tags":["monsters"],"responses":{"200":{"description":"OK"},"400":{"description":"Bad Request"},"401":{"description":"Unauthorized"},"403":{"description":"Forbidden"},"404":{"description":"Not Found"},"422":{"description":"Unprocessable Entity"},"500":{"description":"Internal"}},"security":[{"bearerAuth":[]}],"parameters":[{"name":"id","in":"path","required":true,"schema":{"type":"string"}}]},"patch":{"tags":["monsters"],"responses":{"200":{"description":"OK"},"400":{"description":"Bad Request"},"401":{"description":"Unauthorized"},"403":{"description":"Forbidden"},"404":{"description":"Not Found"},"422":{"description":"Unprocessable Entity"},"500":{"description":"Internal"}},"security":[{"bearerAuth":[]}],"parameters":[{"name":"id","in":"path","required":true,"schema":{"type":"string"}},{"name":"availability","in":"query","required":true,"schema":{"type":"boolean"}}]}},"/dnd5e/spells":{"get":{"tags":["spells"],"responses":{"200":{"description":"OK"},"400":{"description":"Bad Request"},"401":{"description":"Unauthorized"},"403":{"description":"Forbidden"},"404":{"description":"Not Found"},"422":{"description":"Unprocessable Entity"},"500":{"description":"Internal"}},"security":[{"bearerAuth":[]}]}},"/dnd5e/spells/disabled":{"get":{"tags":["spells"],"responses":{"200":{"description":"OK"},"400":{"description":"Bad Request"},"401":{"description":"Unauthorized"},"403":{"description":"Forbidden"},"404":{"description":"Not Found"},"422":{"description":"Unprocessable Entity"},"500":{"description":"Internal"}},"security":[{"bearerAuth":[]}]}},"/dnd5e/spells/{id}":{"get":{"tags":["spells"],"responses":{"200":{"description":"OK"},"400":{"description":"Bad Request"},"401":{"description":"Unauthorized"},"403":{"description":"Forbidden"},"404":{"description":"Not Found"},"422":{"description":"Unprocessable Entity"},"500":{"description":"Internal"}},"security":[{"bearerAuth":[]}],"parameters":[{"name":"id","in":"path","required":true,"schema":{"type":"string"}}]},"patch":{"tags":["spells"],"responses":{"200":{"description":"OK"},"400":{"description":"Bad Request"},"401":{"description":"Unauthorized"},"403":{"description":"Forbidden"},"404":{"description":"Not Found"},"422":{"description":"Unprocessable Entity"},"500":{"description":"Internal"}},"security":[{"bearerAuth":[]}],"parameters":[{"name":"id","in":"path","required":true,"schema":{"type":"string"}},{"name":"availability","in":"query","required":true,"schema":{"type":"boolean"}}]}}},"components":{"securitySchemes":{"bearerAuth":{"type":"http","scheme":"bearer","bearerFormat":"JWT"}}}}